jdict/__init__.py
jdict/transformer.py
pyjdict-1.0.6.dist-info/LICENSE.md
pyjdict-1.0.6.dist-info/WHEEL
pyjdict-1.0.6.dist-info/METADATA
pyjdict-1.0.6.dist-info/RECORD
