Metadata-Version: 2.1
Name: pyjdict
Version: 1.0.6
Summary: JavaScript-like Python dictionary
Author-email: BST Labs <bstlabs@caios.io>
Requires-Python: >=3.8
Classifier: License :: OSI Approved :: MIT License
Requires-Dist: black >=21.9b0 ; extra == "dev"
Requires-Dist: pylint >=2.12.2 ; extra == "dev"
Requires-Dist: isort >=5.9.3 ; extra == "dev"
Requires-Dist: autoflake >=1.4 ; extra == "dev"
Requires-Dist: flake8 >=4.0.1 ; extra == "dev"
Requires-Dist: pre-commit >=2.17.0 ; extra == "dev"
Requires-Dist: pytype >=2022.1.31 ; extra == "dev"
Requires-Dist: mkdocs-material >=8.1.2 ; extra == "doc"
Project-URL: Documentation, https://github.com/bstlabs/py-jdict
Project-URL: Home, https://github.com/bstlabs/py-jdict
Project-URL: Source, https://github.com/bstlabs/py-jdict
Provides-Extra: dev
Provides-Extra: doc
